tuick/__init__.py
tuick/ansi.py
tuick/cli.py
tuick/console.py
tuick/editor.py
tuick/errorformat.py
tuick/fzf.py
tuick/monitor.py
tuick/py.typed
tuick/reload_socket.py
tuick/shell.py
tuick/theme.py
tuick/tool_registry.py
tuick-0.1.5.dist-info/METADATA
tuick-0.1.5.dist-info/WHEEL
tuick-0.1.5.dist-info/entry_points.txt
tuick-0.1.5.dist-info/licenses/LICENSE
tuick-0.1.5.dist-info/RECORD
