Metadata-Version: 2.4
Name: tuick
Version: 0.1.5
Summary: Terminal based browser for source code errors.
Author-email: David Allouche <david@ddaa.net>
License: MIT
License-File: LICENSE
Requires-Python: >=3.14
Requires-Dist: requests>=2.32.5
Requires-Dist: rich>=14.2.0
Requires-Dist: typer>=0.20.0
